CHANGELOG.md
LICENSE
README.md
examples/README.md
examples/led_rainbow.py
examples/read_adcs.py
examples/read_encoders.py
examples/read_gpios.py
examples/read_internals.py
examples/reset_inventor.py
examples/set_gpios.py
examples/audio/ahoy.wav
examples/audio/motor_song.py
examples/audio/play_sound_aplay.py
examples/audio/play_sound_pygame.py
examples/audio/random_droid.py
examples/extras/gpio_encoder.py
examples/extras/read_servo_pins.py
examples/extras/read_ultrasound.py
examples/extras/servo_pin_motor.py
examples/extras/set_servo_pins.py
examples/extras/watchdog_reset.py
examples/motors/driving_sequence.py
examples/motors/dual_motors.py
examples/motors/motor_wave.py
examples/motors/position_control.py
examples/motors/position_on_velocity_control.py
examples/motors/position_wave.py
examples/motors/reactive_encoder.py
examples/motors/single_motor.py
examples/motors/velocity_control.py
examples/motors/tuning/motor_profiler.py
examples/motors/tuning/position_on_velocity_tuning.py
examples/motors/tuning/position_tuning.py
examples/motors/tuning/velocity_tuning.py
examples/servos/calibration.py
examples/servos/multiple_servos.py
examples/servos/servo_wave.py
examples/servos/simple_easing.py
examples/servos/single_servo.py
inventorhatmini/__init__.py
inventorhatmini/errors.py
inventorhatmini/plasma.py
inventorhatmini-1.0.0.dist-info/METADATA
inventorhatmini-1.0.0.dist-info/WHEEL
inventorhatmini-1.0.0.dist-info/licenses/LICENSE
inventorhatmini-1.0.0.dist-info/RECORD
